MANIFEST.in
README.md
pyproject.toml
setup.py
PySAIS/COPYING
PySAIS/__init__.py
PySAIS/_sais.py
PySAIS/_sais32.c
PySAIS/_sais32.pyx
PySAIS/_sais64.c
PySAIS/_sais64.pyx
PySAIS/sais.c
PySAIS/sais.h
PySAIS/sais32.c
PySAIS/sais32.h
PySAIS/sais64.c
PySAIS/sais64.h
PySAIS.egg-info/PKG-INFO
PySAIS.egg-info/SOURCES.txt
PySAIS.egg-info/dependency_links.txt
PySAIS.egg-info/requires.txt
PySAIS.egg-info/top_level.txt