Metadata-Version: 1.0
Name: PySAIS
Version: 1.0.7
Summary: Suffix array computation with induced sorting algorithm.
Home-page: https://bitbucket.org/alex-warwickvesztrocy/pysais
Author: Alex Warwick Vesztrocy
Author-email: alex@warwickvesztrocy.co.uk
License: MIT
Platform: UNKNOWN
